bframe/__init__.py
bframe/_except.py
bframe/config.py
bframe/ctx.py
bframe/frame.py
bframe/generics.py
bframe/local.py
bframe/logger.py
bframe/route.py
bframe/scaffold.py
bframe/serizlizer.py
bframe/server.py
bframe/sessions.py
bframe/testing.py
bframe/utils.py
bframe/view.py
bframe/wrappers.py
bframe/wsgi.py
bframe/yellowprint.py
bframe-0.0.17.dist-info/LICENSE
bframe-0.0.17.dist-info/METADATA
bframe-0.0.17.dist-info/WHEEL
bframe-0.0.17.dist-info/top_level.txt
bframe-0.0.17.dist-info/RECORD
