Metadata-Version: 2.1
Name: bframe
Version: 0.0.17
Summary: A simple python web server frame
Author-email: Bean-jun <1342104001@qq.com>
Project-URL: Homepage, https://github.com/Bean-jun/bframe
Project-URL: Bug Tracker, https://github.com/Bean-jun/bframe/issues
Classifier: License :: OSI Approved :: MIT License
Classifier: Programming Language :: Python :: 3
Classifier: Environment :: Web Environment
Requires-Python: >=3.8
License-File: LICENSE
